gammatone/__init__.py
gammatone/__main__.py
gammatone/fftweight.py
gammatone/filters.py
gammatone/gtgram.py
gammatone/plot.py
Gammatone-1.0.3.dist-info/COPYING
Gammatone-1.0.3.dist-info/METADATA
Gammatone-1.0.3.dist-info/WHEEL
Gammatone-1.0.3.dist-info/entry_points.txt
Gammatone-1.0.3.dist-info/top_level.txt
Gammatone-1.0.3.dist-info/RECORD
