Metadata-Version: 2.1
Name: Gammatone
Version: 1.0.3
Home-page: https://github.com/Lightning-Sandbox/gammatone
Download-URL: https://github.com/Lightning-Sandbox/gammatone/archive/main.zip
Author: Jason Heeris
Author-email: Jason@Heeri.me
Classifier: Environment :: Console
Classifier: Natural Language :: English
Classifier: Development Status :: 4 - Beta
Classifier: Intended Audience :: Developers
Classifier: Topic :: Scientific/Engineering :: Information Analysis
Classifier: Operating System :: OS Independent
Classifier: Programming Language :: Python :: 3
Requires-Python: >=3.8
License-File: COPYING
Requires-Dist: numpy
Requires-Dist: scipy
Requires-Dist: matplotlib
Provides-Extra: test
Requires-Dist: pytest; extra == "test"
Requires-Dist: mock; extra == "test"
